jeepney_objects/__init__.py
jeepney_objects/dbus_object.py
jeepney_objects-0.2.0.dist-info/LICENSE
jeepney_objects-0.2.0.dist-info/METADATA
jeepney_objects-0.2.0.dist-info/WHEEL
jeepney_objects-0.2.0.dist-info/top_level.txt
jeepney_objects-0.2.0.dist-info/RECORD
